markov_clustering/__init__.py
markov_clustering/drawing.py
markov_clustering/mcl.py
markov_clustering/utils.py
markov_clustering-0.0.3.dev0.dist-info/METADATA
markov_clustering-0.0.3.dev0.dist-info/RECORD
markov_clustering-0.0.3.dev0.dist-info/WHEEL
markov_clustering-0.0.3.dev0.dist-info/top_level.txt
